q39.v
module seq(x1,x2,z);
input x1,x2;
output z;
reg k,z;
always @(x1,x2)
begin
//$display("entered");
if(x1==1'b0 && x2==1'b0)
begin
//$display("first if");
 k=1'b0;
 z=1'b0;
end
if(x1==1'b1 || x2==1'b1)
begin
 if (k!=1'b1)
  z=1'b1;
 else
  z=1'b0;
end
if(x1==1'b1 && x2==1'b1)
begin
 k=1'b1;
 z=1'b0;
end
end
endmodule

module testseq;
reg x1,x2;
wire z;
seq se_q(x1,x2,z);
initial begin
$dumpfile("39.vcd");
$dumpvars(0,testseq);
#5 x1=0;x2=0;
#5 x1=0;x2=1;
#5 x1=1;x2=0;
#5 x1=1;x2=1;
#5 x1=0;x2=1;
#5 x1=0;x2=0;
#5 x1=1;x2=0;
end
initial
$monitor($time," x1=%b,x2=%b,z=%b",x1,x2,z);
endmodule

39.vcd
$date
	Sat Nov 10 16:01:25 2018
$end
$version
	Icarus Verilog
$end
$timescale
	1s
$end
$scope module testseq $end
$var wire 1 ! z $end
$var reg 1 " x1 $end
$var reg 1 # x2 $end
$scope module se_q $end
$var wire 1 " x1 $end
$var wire 1 # x2 $end
$var reg 1 $ k $end
$var reg 1 ! z $end
$upscope $end
$upscope $end
$enddefinitions $end
#0
$dumpvars
x$
x#
x"
x!
$end
#5
0!
0$
0#
0"
#10
1!
1#
#15
0#
1"
#20
0!
1$
1#
#25
0"
#30
0$
0#
#35
1!
1"
