49.v
module shift(w,cntrl,clk,y,k);
input [3:0]w;
input cntrl,clk;
output reg [3:0]y;
output reg k;
integer d;
integer i;
initial
d=0;
always @(clk)
begin
if(cntrl==1)
begin

d++;
//$display("d=%b",d);
for(i=0;i<4;i++)
begin 
if((i+d)<=3)
y[i]=w[i+d];
else
y[i]=0;
if(i==0)
k=w[d-1];
//$display("d=%b",d);
end
end
else if(cntrl==0)
begin
//$display("hello");
d=0;
y=w;
k=0;
end
end
endmodule

module test;
reg [3:0]w;
reg cntrl,clk;
wire [3:0]y;
wire k;
shift sh(w,cntrl,clk,y,k);
initial
clk=1'b0;
always
#5 clk=~clk;
initial
begin
$dumpfile("49.vcd");
$dumpvars(0,test);
w=4'b1111;
 cntrl=1;
#20 cntrl=0;
#10 cntrl=1;
end
always @(clk)
$monitor($time," w=%b,cntrl=%b,y=%b,k=%b",w,cntrl,y,k);
initial
#40 $finish;
endmodule

49.vcd
$date
	Sun Nov 25 21:53:33 2018
$end
$version
	Icarus Verilog
$end
$timescale
	1s
$end
$scope module test $end
$var wire 4 ! y [3:0] $end
$var wire 1 " k $end
$var reg 1 # clk $end
$var reg 1 $ cntrl $end
$var reg 4 % w [3:0] $end
$scope module sh $end
$var wire 1 # clk $end
$var wire 1 $ cntrl $end
$var wire 4 & w [3:0] $end
$var reg 1 " k $end
$var reg 4 ' y [3:0] $end
$var integer 32 ( d [31:0] $end
$var integer 32 ) i [31:0] $end
$upscope $end
$upscope $end
$enddefinitions $end
#0
$dumpvars
b100 )
b1 (
b111 '
b1111 &
b1111 %
1$
0#
1"
b111 !
$end
#5
b11 !
b11 '
b100 )
b10 (
1#
#10
b1 !
b1 '
b100 )
b11 (
0#
#15
b0 !
b0 '
b100 )
b100 (
1#
#20
0"
b1111 !
b1111 '
b0 (
0#
0$
#25
1#
#30
b111 !
b111 '
1"
b100 )
b1 (
0#
1$
#35
b11 !
b11 '
b100 )
b10 (
1#
#40
b1 !
b1 '
b100 )
b11 (
0#
