50qb.v
module Prob_5_38b (x_in, clock, reset_b,next_state);
input x_in,clock,reset_b;
output [1:0] next_state;
parameter s0 = 2'b00, s1 = 2'b01, s2 = 2'b10, s3 = 2'b11;
reg [1: 0] state, next_state;
always @ (posedge clock, negedge reset_b)
if (reset_b == 0) state <= s0;
else state <= next_state;
always @ (state, x_in) begin
next_state = s0;
case (state)
s0: if (x_in == 0) next_state = s0;
else if (x_in == 1) next_state = s3;
s1: if (x_in == 0) next_state = s1;
else if (x_in == 1) next_state = s2;
s2: if (x_in == 0) next_state = s2;
else if (x_in == 1) next_state = s0;
s3: if (x_in == 0) next_state = s3;
else if (x_in == 1) next_state = s1;
default: next_state = s0;
endcase
end
endmodule

module t_Prob_5_38b ();
reg x_in, clk, reset_b;
wire [1:0] next_state;
Prob_5_38b M0 ( x_in, clk, reset_b,next_state);
initial #350$finish;
initial begin 
$dumpfile("50qb.vcd");
$dumpvars(0,t_Prob_5_38b);
clk = 0; forever #5 clk = ~clk; end
initial $monitor($time," next_state=%b",next_state);
initial fork
#2 reset_b = 1;
#3 reset_b = 0; // Initialize to s0
#4 reset_b = 1;
#2 x_in = 0;
#20 x_in = 1;
#60 x_in = 0;
#80 x_in = 1;
#90 x_in = 0;
#110 x_in = 1;
#120 x_in = 0;
#140 x_in = 1;
#150 x_in = 0;
#170 x_in= 1;
join
endmodule

50qb.vcd
$date
	Sat Nov 10 09:06:26 2018
$end
$version
	Icarus Verilog
$end
$timescale
	1s
$end
$scope module t_Prob_5_38b $end
$var wire 2 ! next_state [1:0] $end
$var reg 1 " clk $end
$var reg 1 # reset_b $end
$var reg 1 $ x_in $end
$scope module M0 $end
$var wire 1 " clock $end
$var wire 1 # reset_b $end
$var wire 1 $ x_in $end
$var reg 2 % next_state [1:0] $end
$var reg 2 & state [1:0] $end
$upscope $end
$upscope $end
$enddefinitions $end
#0
$dumpvars
bx &
bx %
x$
x#
0"
bx !
$end
#2
b0 !
b0 %
1#
0$
#3
b0 &
0#
#4
1#
#5
1"
#10
0"
#15
1"
#20
b11 !
b11 %
0"
1$
#25
b1 !
b1 %
b11 &
1"
#30
0"
#35
b10 !
b10 %
b1 &
1"
#40
0"
#45
b0 !
b0 %
b10 &
1"
#50
0"
#55
b11 !
b11 %
b0 &
1"
#60
b0 !
b0 %
0"
0$
#65
1"
#70
0"
#75
1"
#80
b11 !
b11 %
0"
1$
#85
b1 !
b1 %
b11 &
1"
#90
b11 !
b11 %
0"
0$
#95
1"
#100
0"
#105
1"
#110
b1 !
b1 %
0"
1$
#115
b10 !
b10 %
b1 &
1"
#120
b1 !
b1 %
0"
0$
#125
1"
#130
0"
#135
1"
#140
b10 !
b10 %
0"
1$
#145
b0 !
b0 %
b10 &
1"
#150
b10 !
b10 %
0"
0$
#155
1"
#160
0"
#165
1"
#170
b0 !
b0 %
0"
1$
#175
b11 !
b11 %
b0 &
1"
#180
0"
#185
b1 !
b1 %
b11 &
1"
#190
0"
#195
b10 !
b10 %
b1 &
1"
#200
0"
#205
b0 !
b0 %
b10 &
1"
#210
0"
#215
b11 !
b11 %
b0 &
1"
#220
0"
#225
b1 !
b1 %
b11 &
1"
#230
0"
#235
b10 !
b10 %
b1 &
1"
#240
0"
#245
b0 !
b0 %
b10 &
1"
#250
0"
#255
b11 !
b11 %
b0 &
1"
#260
0"
#265
b1 !
b1 %
b11 &
1"
#270
0"
#275
b10 !
b10 %
b1 &
1"
#280
0"
#285
b0 !
b0 %
b10 &
1"
#290
0"
#295
b11 !
b11 %
b0 &
1"
#300
0"
#305
b1 !
b1 %
b11 &
1"
#310
0"
#315
b10 !
b10 %
b1 &
1"
#320
0"
#325
b0 !
b0 %
b10 &
1"
#330
0"
#335
b11 !
b11 %
b0 &
1"
#340
0"
#345
b1 !
b1 %
b11 &
1"
